webnotifier/__init__.py
webnotifier/webnotifier.py
webnotifier-0.1.1.dist-info/LICENSE
webnotifier-0.1.1.dist-info/METADATA
webnotifier-0.1.1.dist-info/WHEEL
webnotifier-0.1.1.dist-info/top_level.txt
webnotifier-0.1.1.dist-info/RECORD
