Metadata-Version: 2.1
Name: webnotifier
Version: 0.1.1
Summary: A package for notifying any webpage change
Home-page: https://github.com/polmp/webnotifier
Author: Pol MP
Author-email: pol.moreno30@gmail.com
License: UNKNOWN
Platform: UNKNOWN
Classifier: Programming Language :: Python :: 3
Classifier: Development Status :: 4 - Beta
Classifier: License :: OSI Approved :: MIT License
Classifier: Operating System :: OS Independent
Requires-Dist: requests (>=2.21.0)
Requires-Dist: lxml (>=4.3.3)
